Fs/__init__.py
Fs/main.py
image_vault-1.0.2.dist-info/LICENSE
image_vault-1.0.2.dist-info/METADATA
image_vault-1.0.2.dist-info/WHEEL
image_vault-1.0.2.dist-info/entry_points.txt
image_vault-1.0.2.dist-info/top_level.txt
image_vault-1.0.2.dist-info/RECORD
