Metadata-Version: 2.1
Name: image_vault
Version: 1.0.2
Summary: it is a tool for encrypting images
Author: Tanish
Author-email: sharmatanish0907@gmail.com
Keywords: python,cryptography,image_vault,vault,encrypt,encryption,fs
License-File: LICENSE
Requires-Dist: pillow
Requires-Dist: cryptography
Requires-Dist: click
